trashman-1.5.0.dist-info/WHEEL
trashman-1.5.0.dist-info/top_level.txt
trashman-1.5.0.dist-info/RECORD
trashman-1.5.0.dist-info/metadata.json
trashman-1.5.0.dist-info/DESCRIPTION.rst
trashman-1.5.0.dist-info/entry_points.txt
trashman-1.5.0.dist-info/METADATA
trashman/tmds.py
trashman/__main__.py
trashman/__init__.py
trashman/backends/trash.py
trashman/backends/xdgtrash.py
trashman/backends/dummytrash.py
trashman/backends/__init__.py
trashman-1.5.0.data/data/share/man/man8/trashman.8.gz
trashman-1.5.0.data/data/share/locale/en/LC_MESSAGES/trashman.mo
trashman-1.5.0.data/data/share/locale/pl/LC_MESSAGES/trashman.mo
trashman-1.5.0.data/data/share/zsh/site-functions/_trash
