Metadata-Version: 2.0
Name: trashman
Version: 1.5.0
Summary: A Python trash manager.
Home-page: https://github.com/Kwpolska/trashman
Author: Chris Warrick
Author-email: chris@chriswarrick.com
License: 3-clause BSD
Platform: any
Classifier: Development Status :: 5 - Production/Stable
Classifier: Environment :: Console
Classifier: Intended Audience :: End Users/Desktop
Classifier: License :: OSI Approved :: BSD License
Classifier: Natural Language :: English
Classifier: Operating System :: POSIX :: Linux
Classifier: Programming Language :: Python
Classifier: Programming Language :: Python :: 2
Classifier: Programming Language :: Python :: 3
Classifier: Topic :: Utilities
